splora/__init__.py
splora/_version.py
splora/io.py
splora/splora.py
splora/utils.py
splora/cli/__init__.py
splora/cli/run.py
splora/deconvolution/__init__.py
splora/deconvolution/debiasing.py
splora/deconvolution/fista.py
splora/deconvolution/hrf_matrix.py
splora/tests/__init__.py
splora/tests/conftest.py
splora/tests/test_debiasing.py
splora/tests/test_fista.py
splora/tests/test_hrf_matrix.py
splora/tests/test_integration.py
splora/tests/test_io.py
splora/tests/utils.py
splora-0.0.1a0.dist-info/LICENSE
splora-0.0.1a0.dist-info/METADATA
splora-0.0.1a0.dist-info/WHEEL
splora-0.0.1a0.dist-info/entry_points.txt
splora-0.0.1a0.dist-info/top_level.txt
splora-0.0.1a0.dist-info/RECORD
