Metadata-Version: 2.1
Name: splora
Version: 0.0.1a0
Summary: Python library to estimate neuronal activity-related, activity-inducing and innovaition signals, as well as estimating global fluctuations.
Home-page: https://github.com/eurunuela/splora
Author: Eneko Uruñuela
Maintainer: Eneko Uruñuela
Maintainer-email: e.urunuela@bcbl.eu
License: Apache-2.0
Download-URL: https://github.com/eurunuela/splora
Platform: OS Independent
Classifier: Development Status :: 5 - Production/Stable
Classifier: Intended Audience :: Science/Research
Classifier: License :: OSI Approved :: Apache Software License
Classifier: Programming Language :: Python :: 3.6
Classifier: Programming Language :: Python :: 3.7
Provides: splora
Requires-Python: >=3.6.1
License-File: LICENSE
Requires-Dist: nibabel
Requires-Dist: nilearn
Requires-Dist: numpy
Requires-Dist: PyWavelets
Requires-Dist: scipy
Requires-Dist: sklearn
Requires-Dist: tqdm
Provides-Extra: all
Requires-Dist: sphinx (>=2.0) ; extra == 'all'
Requires-Dist: sphinx-argparse ; extra == 'all'
Requires-Dist: sphinx-rtd-theme ; extra == 'all'
Requires-Dist: flake8 (>=3.7) ; extra == 'all'
Requires-Dist: flake8-docstrings (>=1.5) ; extra == 'all'
Requires-Dist: pytest (>=5.3) ; extra == 'all'
Requires-Dist: pytest-cov ; extra == 'all'
Provides-Extra: doc
Requires-Dist: sphinx (>=2.0) ; extra == 'doc'
Requires-Dist: sphinx-argparse ; extra == 'doc'
Requires-Dist: sphinx-rtd-theme ; extra == 'doc'
Provides-Extra: style
Requires-Dist: flake8 (>=3.7) ; extra == 'style'
Requires-Dist: flake8-docstrings (>=1.5) ; extra == 'style'
Provides-Extra: test
Requires-Dist: pytest (>=5.3) ; extra == 'test'
Requires-Dist: pytest-cov ; extra == 'test'
Requires-Dist: sphinx (>=2.0) ; extra == 'test'
Requires-Dist: sphinx-argparse ; extra == 'test'
Requires-Dist: sphinx-rtd-theme ; extra == 'test'
Requires-Dist: flake8 (>=3.7) ; extra == 'test'
Requires-Dist: flake8-docstrings (>=1.5) ; extra == 'test'
